shipyard_mode/__init__.py
shipyard_mode/cli/__init__.py
shipyard_mode/cli/authtest.py
shipyard_mode/cli/download_result_as_file.py
shipyard_mode/cli/exit_codes.py
shipyard_mode/cli/run_report.py
shipyard_mode/mode.py
shipyard_mode-0.2.1.dist-info/METADATA
shipyard_mode-0.2.1.dist-info/WHEEL
shipyard_mode-0.2.1.dist-info/RECORD
