Metadata-Version: 2.1
Name: shipyard-mode
Version: 0.2.1
Summary: A local client for connecting and working with Mode
License: Apache 2.0
Author: wrp801
Author-email: wespoulsen@gmail.com
Requires-Python: >=3.9,<4.0
Classifier: License :: Other/Proprietary License
Classifier: Programming Language :: Python :: 3
Classifier: Programming Language :: Python :: 3.9
Classifier: Programming Language :: Python :: 3.10
Classifier: Programming Language :: Python :: 3.11
Requires-Dist: requests (>=2.31.0,<3.0.0)
Requires-Dist: shipyard-bp-utils (>=1.2.1,<2.0.0)
Requires-Dist: shipyard-templates (>=0.8.2,<0.9.0)
